givt_pytorch/__init__.py
givt_pytorch/config.py
givt_pytorch/data.py
givt_pytorch/model.py
givt_pytorch/trainer.py
givt_pytorch-0.0.3.dist-info/LICENSE
givt_pytorch-0.0.3.dist-info/METADATA
givt_pytorch-0.0.3.dist-info/WHEEL
givt_pytorch-0.0.3.dist-info/top_level.txt
givt_pytorch-0.0.3.dist-info/RECORD
