Metadata-Version: 2.1
Name: givt_pytorch
Version: 0.0.3
Summary: A partial implementation of Generative Infinite Vocabulary Transformer (GIVT) from Google Deepmind, in PyTorch.
Home-page: https://github.com/elyxlz/givt-pytorch
Author: Elio Pascarelli
Author-email: elio@pascarelli.com
License: MIT
Classifier: Development Status :: 4 - Beta
Classifier: Intended Audience :: Developers
Classifier: Topic :: Scientific/Engineering :: Artificial Intelligence
Classifier: License :: OSI Approved :: MIT License
Classifier: Programming Language :: Python :: 3.6
Requires-Python: >=3.9
License-File: LICENSE
Requires-Dist: transformers
Requires-Dist: torch
Requires-Dist: python-dotenv
Requires-Dist: einops
Requires-Dist: ema-pytorch >=0.3.2
Provides-Extra: train
Requires-Dist: accelerate ; extra == 'train'
Requires-Dist: wandb ; extra == 'train'
Requires-Dist: tqdm ; extra == 'train'
